yu_mcp_demo/__init__.py
yu_mcp_demo-0.3.0.dist-info/METADATA
yu_mcp_demo-0.3.0.dist-info/WHEEL
yu_mcp_demo-0.3.0.dist-info/entry_points.txt
yu_mcp_demo-0.3.0.dist-info/RECORD
