Metadata-Version: 2.4
Name: yu-mcp-demo
Version: 0.3.0
Summary: A demo MCP server with basic arithmetic operations (add, subtract, multiply, divide) and greeting features.
Author-email: plion818 <patrick89818pp@gmail.com>
Requires-Python: >=3.12
Requires-Dist: mcp[cli]>=1.24.0
